odoo/addons/shopinvader_api_address_shipping_note/README.rst
odoo/addons/shopinvader_api_address_shipping_note/__init__.py
odoo/addons/shopinvader_api_address_shipping_note/__manifest__.py
odoo/addons/shopinvader_api_address_shipping_note/schemas.py
odoo/addons/shopinvader_api_address_shipping_note/i18n/shopinvader_api_address_shipping_note.pot
odoo/addons/shopinvader_api_address_shipping_note/readme/CONTRIBUTORS.rst
odoo/addons/shopinvader_api_address_shipping_note/readme/DESCRIPTION.rst
odoo/addons/shopinvader_api_address_shipping_note/static/description/index.html
odoo/addons/shopinvader_api_address_shipping_note/tests/__init__.py
odoo/addons/shopinvader_api_address_shipping_note/tests/test_shopinvader_api_address_shipping_note.py
odoo_addon_shopinvader_api_address_shipping_note-16.0.1.0.0.6.dist-info/METADATA
odoo_addon_shopinvader_api_address_shipping_note-16.0.1.0.0.6.dist-info/WHEEL
odoo_addon_shopinvader_api_address_shipping_note-16.0.1.0.0.6.dist-info/top_level.txt
odoo_addon_shopinvader_api_address_shipping_note-16.0.1.0.0.6.dist-info/RECORD
