Metadata-Version: 2.1
Name: odoo-addon-shopinvader_api_address_shipping_note
Version: 16.0.1.0.0.6
Summary: Adds a shipping note on schemas of services to manage Shipping Addresses
Home-page: https://github.com/shopinvader/odoo-shopinvader
Author: ACSONE SA/NV
License: AGPL-3
Classifier: Programming Language :: Python
Classifier: Framework :: Odoo
Classifier: Framework :: Odoo :: 16.0
Classifier: License :: OSI Approved :: GNU Affero General Public License v3
Requires-Python: >=3.10
Requires-Dist: odoo-addon-shopinvader-address-shipping-note<16.1dev,>=16.0dev
Requires-Dist: odoo-addon-shopinvader-api-address<16.1dev,>=16.0dev
Requires-Dist: odoo<16.1dev,>=16.0a
